[
  {
    "title": "MySQL Developer",
    "company": "Wolken Software",
    "location": "Bengaluru, Karnataka, India",
    "link": "https://in.linkedin.com/jobs/view/mysql-developer-at-wolken-software-4306131128?position=1&pageNum=0&refId=JkS6yXkR3kV69mLxbXFQEg%3D%3D&trackingId=%2FnPO1du1sPBrt91O0mE1Kg%3D%3D",
    "source": "LinkedIn",
    "scraped_date": "2026-03-23",
    "status": "new"
  },
  {
    "title": "Bootloader Developer",
    "company": "L&T Technology Services",
    "location": "Bengaluru, Karnataka, India",
    "link": "https://in.linkedin.com/jobs/view/bootloader-developer-at-l-t-technology-services-4385902751?position=2&pageNum=0&refId=JkS6yXkR3kV69mLxbXFQEg%3D%3D&trackingId=U4D0ZQUR2EoIJxiylGuolg%3D%3D",
    "source": "LinkedIn",
    "scraped_date": "2026-03-23",
    "status": "new"
  },
  {
    "title": "Developer",
    "company": "Wipro",
    "location": "Bengaluru, Karnataka, India",
    "link": "https://in.linkedin.com/jobs/view/developer-at-wipro-4381587496?position=3&pageNum=0&refId=JkS6yXkR3kV69mLxbXFQEg%3D%3D&trackingId=1hBluHXZ6pz8e2rROR56fQ%3D%3D",
    "source": "LinkedIn",
    "scraped_date": "2026-03-23",
    "status": "new"
  },
  {
    "title": "Developer",
    "company": "SAP",
    "location": "Bengaluru, Karnataka, India",
    "link": "https://in.linkedin.com/jobs/view/developer-at-sap-4377918368?position=4&pageNum=0&refId=JkS6yXkR3kV69mLxbXFQEg%3D%3D&trackingId=9qJn1Jjhi0C9hrsGN4XXkg%3D%3D",
    "source": "LinkedIn",
    "scraped_date": "2026-03-23",
    "status": "new"
  },
  {
    "title": "Developer",
    "company": "Sapiens",
    "location": "Bengaluru, Karnataka, India",
    "link": "https://in.linkedin.com/jobs/view/developer-at-sapiens-4378160292?position=5&pageNum=0&refId=JkS6yXkR3kV69mLxbXFQEg%3D%3D&trackingId=iuqCHVeLb8ZNcNLQdfZOcg%3D%3D",
    "source": "LinkedIn",
    "scraped_date": "2026-03-23",
    "status": "new"
  },
  {
    "title": "Developer (m/f/d)",
    "company": "Deutsche Telekom",
    "location": "Bengaluru, Karnataka, India",
    "link": "https://in.linkedin.com/jobs/view/developer-m-f-d-at-deutsche-telekom-4383499737?position=6&pageNum=0&refId=JkS6yXkR3kV69mLxbXFQEg%3D%3D&trackingId=06IV9tGfqpVJ4x4I%2BjV4hg%3D%3D",
    "source": "LinkedIn",
    "scraped_date": "2026-03-23",
    "status": "new"
  },
  {
    "title": "Accolade Developer",
    "company": "Tata Elxsi",
    "location": "Bengaluru, Karnataka, India",
    "link": "https://in.linkedin.com/jobs/view/accolade-developer-at-tata-elxsi-4383234396?position=7&pageNum=0&refId=JkS6yXkR3kV69mLxbXFQEg%3D%3D&trackingId=MWHcMKA2sF2JcR9TqS5YOg%3D%3D",
    "source": "LinkedIn",
    "scraped_date": "2026-03-23",
    "status": "new"
  },
  {
    "title": "YANG Developer",
    "company": "Infosys",
    "location": "Bengaluru East, Karnataka, India",
    "link": "https://in.linkedin.com/jobs/view/yang-developer-at-infosys-4367596689?position=8&pageNum=0&refId=JkS6yXkR3kV69mLxbXFQEg%3D%3D&trackingId=n6NExxOE8wtiqBxF9JS6NQ%3D%3D",
    "source": "LinkedIn",
    "scraped_date": "2026-03-23",
    "status": "new"
  },
  {
    "title": "MySQL Expert Developer",
    "company": "TalentMicro",
    "location": "Bengaluru, Karnataka, India",
    "link": "https://in.linkedin.com/jobs/view/mysql-expert-developer-at-talentmicro-4388638577?position=9&pageNum=0&refId=JkS6yXkR3kV69mLxbXFQEg%3D%3D&trackingId=zVTxsdcmucSViKx3AlbnrQ%3D%3D",
    "source": "LinkedIn",
    "scraped_date": "2026-03-23",
    "status": "new"
  },
  {
    "title": "DEVELOPER",
    "company": "Wipro",
    "location": "Bengaluru, Karnataka, India",
    "link": "https://in.linkedin.com/jobs/view/developer-at-wipro-4379794374?position=10&pageNum=0&refId=JkS6yXkR3kV69mLxbXFQEg%3D%3D&trackingId=LIW1scuNZ3INm7QWBlQENg%3D%3D",
    "source": "LinkedIn",
    "scraped_date": "2026-03-23",
    "status": "new"
  },
  {
    "title": "Developer",
    "company": "Cognizant",
    "location": "Bangalore Urban, Karnataka, India",
    "link": "https://in.linkedin.com/jobs/view/developer-at-cognizant-4325370332?position=11&pageNum=0&refId=JkS6yXkR3kV69mLxbXFQEg%3D%3D&trackingId=jxG%2FltU1hSEUXQzI0WygOg%3D%3D",
    "source": "LinkedIn",
    "scraped_date": "2026-03-23",
    "status": "new"
  },
  {
    "title": "Developer",
    "company": "Temenos",
    "location": "Bengaluru, Karnataka, India",
    "link": "https://in.linkedin.com/jobs/view/developer-at-temenos-4369083267?position=12&pageNum=0&refId=JkS6yXkR3kV69mLxbXFQEg%3D%3D&trackingId=LTCdwstM1s%2FY1CjBDn1Eww%3D%3D",
    "source": "LinkedIn",
    "scraped_date": "2026-03-23",
    "status": "new"
  },
  {
    "title": "DEVELOPER",
    "company": "Wipro",
    "location": "Bengaluru, Karnataka, India",
    "link": "https://in.linkedin.com/jobs/view/developer-at-wipro-4379787524?position=13&pageNum=0&refId=JkS6yXkR3kV69mLxbXFQEg%3D%3D&trackingId=tyhvUYdWUQoYSYTkjH2HTg%3D%3D",
    "source": "LinkedIn",
    "scraped_date": "2026-03-23",
    "status": "new"
  },
  {
    "title": "Developer",
    "company": "Birlasoft",
    "location": "Bengaluru, Karnataka, India",
    "link": "https://in.linkedin.com/jobs/view/developer-at-birlasoft-4361869422?position=14&pageNum=0&refId=JkS6yXkR3kV69mLxbXFQEg%3D%3D&trackingId=Q4ZG4J3LADNVRhJbG5BAqw%3D%3D",
    "source": "LinkedIn",
    "scraped_date": "2026-03-23",
    "status": "new"
  },
  {
    "title": "Palantir Developer",
    "company": "Infosys",
    "location": "Bengaluru, Karnataka, India",
    "link": "https://in.linkedin.com/jobs/view/palantir-developer-at-infosys-4366484177?position=15&pageNum=0&refId=JkS6yXkR3kV69mLxbXFQEg%3D%3D&trackingId=SZ6zzv4KuuO45L9b%2FtytNA%3D%3D",
    "source": "LinkedIn",
    "scraped_date": "2026-03-23",
    "status": "new"
  },
  {
    "title": "N/A",
    "company": "N/A",
    "location": "Remote",
    "link": "",
    "source": "Internshala",
    "scraped_date": "2026-03-23",
    "status": "new"
  },
  {
    "title": "N/A",
    "company": "N/A",
    "location": "Remote",
    "link": "",
    "source": "Internshala",
    "scraped_date": "2026-03-23",
    "status": "new"
  },
  {
    "title": "N/A",
    "company": "N/A",
    "location": "Remote",
    "link": "",
    "source": "Internshala",
    "scraped_date": "2026-03-23",
    "status": "new"
  },
  {
    "title": "N/A",
    "company": "N/A",
    "location": "Remote",
    "link": "",
    "source": "Internshala",
    "scraped_date": "2026-03-23",
    "status": "new"
  },
  {
    "title": "N/A",
    "company": "N/A",
    "location": "Remote",
    "link": "",
    "source": "Internshala",
    "scraped_date": "2026-03-23",
    "status": "new"
  },
  {
    "title": "N/A",
    "company": "N/A",
    "location": "Remote",
    "link": "",
    "source": "Internshala",
    "scraped_date": "2026-03-23",
    "status": "new"
  },
  {
    "title": "N/A",
    "company": "N/A",
    "location": "Remote",
    "link": "",
    "source": "Internshala",
    "scraped_date": "2026-03-23",
    "status": "new"
  },
  {
    "title": "N/A",
    "company": "N/A",
    "location": "Remote",
    "link": "",
    "source": "Internshala",
    "scraped_date": "2026-03-23",
    "status": "new"
  },
  {
    "title": "N/A",
    "company": "N/A",
    "location": "Remote",
    "link": "",
    "source": "Internshala",
    "scraped_date": "2026-03-23",
    "status": "new"
  },
  {
    "title": "N/A",
    "company": "N/A",
    "location": "Remote",
    "link": "",
    "source": "Internshala",
    "scraped_date": "2026-03-23",
    "status": "new"
  },
  {
    "title": "N/A",
    "company": "N/A",
    "location": "Remote",
    "link": "",
    "source": "Internshala",
    "scraped_date": "2026-03-23",
    "status": "new"
  },
  {
    "title": "N/A",
    "company": "N/A",
    "location": "Remote",
    "link": "",
    "source": "Internshala",
    "scraped_date": "2026-03-23",
    "status": "new"
  },
  {
    "title": "N/A",
    "company": "N/A",
    "location": "Remote",
    "link": "",
    "source": "Internshala",
    "scraped_date": "2026-03-23",
    "status": "new"
  },
  {
    "title": "N/A",
    "company": "N/A",
    "location": "Remote",
    "link": "",
    "source": "Internshala",
    "scraped_date": "2026-03-23",
    "status": "new"
  },
  {
    "title": "N/A",
    "company": "N/A",
    "location": "Remote",
    "link": "",
    "source": "Internshala",
    "scraped_date": "2026-03-23",
    "status": "new"
  }
]